microdrill
tests
