Metadata-Version: 1.1
Name: microdrill
Version: 0.0.2
Summary: Simple Apache Drill alternative using PySpark
Home-page: https://github.com/globocom/MicroDrill
Author: Globo.com
Author-email: backstage7@corp.globo.com
License: Apache
Keywords: apache drill client parquet hbase pyspark
Platform: UNKNOWN
Classifier: Intended Audience :: Developers
Classifier: License :: OSI Approved :: Apache Software License
Classifier: Programming Language :: Python :: 2.7
